off2txt/__init__.py
off2txt/logger.py
off2txt/off2txt.py
off2txt/options.py
off2txt-0.1.0.dist-info/DESCRIPTION.rst
off2txt-0.1.0.dist-info/entry_points.txt
off2txt-0.1.0.dist-info/METADATA
off2txt-0.1.0.dist-info/metadata.json
off2txt-0.1.0.dist-info/RECORD
off2txt-0.1.0.dist-info/top_level.txt
off2txt-0.1.0.dist-info/WHEEL
