Metadata-Version: 2.0
Name: off2txt
Version: 0.1.0
Summary: off2txt: extract text from Office files
Home-page: https://github.com/bnomis/off2txt
Author: Simon Blanchard
Author-email: bnomis@gmail.com
License: MIT
Keywords: office,text,extract
Platform: macosx
Platform: linux
Platform: unix
Classifier: Development Status :: 5 - Production/Stable
Classifier: Environment :: Console
Classifier: Intended Audience :: Developers
Classifier: License :: OSI Approved :: MIT License
Classifier: Natural Language :: English
Classifier: Operating System :: POSIX
Classifier: Programming Language :: Python :: 2.7
Classifier: Programming Language :: Python :: 3.4
Classifier: Topic :: Office/Business :: Office Suites
Classifier: Topic :: Text Processing
Classifier: Topic :: Utilities
Requires-Dist: lxml
Requires-Dist: openpyxl
Requires-Dist: python-docx
Requires-Dist: python-pptx
